pymltools/__init__.py
pymltools/feature_binning.py
pymltools/shap_significance.py
ml_feature_toolkit-0.1.1.dist-info/LICENSE
ml_feature_toolkit-0.1.1.dist-info/METADATA
ml_feature_toolkit-0.1.1.dist-info/WHEEL
ml_feature_toolkit-0.1.1.dist-info/top_level.txt
ml_feature_toolkit-0.1.1.dist-info/RECORD
