Metadata-Version: 2.1
Name: ml-feature-toolkit
Version: 0.1.1
Summary: A package for analyzing feature interactions in machine learning models
Home-page: https://github.com/HishamSalem/pymltools
Author: Hisham Salem
Author-email: hisham.salem@mail.mcgill.ca
Classifier: Programming Language :: Python :: 3
Classifier: License :: OSI Approved :: MIT License
Classifier: Operating System :: OS Independent
Requires-Python: >=3.6
License-File: LICENSE
Requires-Dist: numpy
Requires-Dist: pandas
Requires-Dist: scikit-learn
Requires-Dist: xgboost
Requires-Dist: shap
Requires-Dist: optbinning
Requires-Dist: SALib
Requires-Dist: scipy
Requires-Dist: statsmodels
Requires-Dist: tqdm
Requires-Dist: matplotlib
Requires-Dist: seaborn
Requires-Dist: joblib
